dokter/__init__.py
dokter/analyzer.py
dokter/main.py
dokter/parser.py
dokter/shellcheck.py
dokter-1.4.2.dist-info/LICENSE
dokter-1.4.2.dist-info/METADATA
dokter-1.4.2.dist-info/WHEEL
dokter-1.4.2.dist-info/entry_points.txt
dokter-1.4.2.dist-info/top_level.txt
dokter-1.4.2.dist-info/RECORD
